{
    "definitions": {
        "image": {
            "type": "object",
            "additionalProperties": false,
            "required": [
                "name",
                "type",
                "position",
                "size",
                "image_url",
                "clickable",
                "draggable"
            ],
            "properties": {
                "name": {
                    "$id": "#/properties/name",
                    "type": "string",
                    "pattern": "^(.*)$"
                },
                "type": {
                    "$id": "#/properties/type",
                    "type": "string",
                    "pattern": "^(.*)$"
                },
                "position": {
                    "$id": "#/properties/position",
                    "type": "object",
                    "additionalProperties": false,
                    "required": [
                        "x",
                        "y"
                    ],
                    "properties": {
                        "x": {
                            "$id": "#/properties/position/properties/x",
                            "type": "integer"
                        },
                        "y": {
                            "$id": "#/properties/position/properties/y",
                            "type": "integer"
                        }
                    }
                },
                "size": {
                    "$id": "#/properties/size",
                    "type": "object",
                    "additionalProperties": false,
                    "required": [
                        "w",
                        "h"
                    ],
                    "properties": {
                        "w": {
                            "$id": "#/properties/size/properties/w",
                            "type": "integer"
                        },
                        "h": {
                            "$id": "#/properties/size/properties/h",
                            "type": "integer"
                        }
                    }
                },
                "image_url": {
                    "$id": "#/properties/image_url",
                    "type": "string",
                    "pattern": "^(.*)$"
                },
                "clickable": {
                    "$id": "#/properties/clickable",
                    "type": "boolean"
                },
                "draggable": {
                    "$id": "#/properties/draggable",
                    "type": "boolean"
                }
            }
        },
        "text": {
            "type": "object",
            "additionalProperties": false,
            "required": [
                "name",
                "type",
                "position",
                "text",
                "font",
                "size",
                "clickable",
                "draggable"
            ],
            "properties": {
                "name": {
                    "$id": "#/properties/name",
                    "type": "string",
                    "pattern": "^(.*)$"
                },
                "type": {
                    "$id": "#/properties/type",
                    "type": "string",
                    "pattern": "^(.*)$"
                },
                "position": {
                    "$id": "#/properties/position",
                    "type": "object",
                    "additionalProperties": false,
                    "required": [
                        "x",
                        "y"
                    ],
                    "properties": {
                        "x": {
                            "$id": "#/properties/position/properties/x",
                            "type": "integer"
                        },
                        "y": {
                            "$id": "#/properties/position/properties/y",
                            "type": "integer"
                        }
                    }
                },
                "text": {
                    "$id": "#/properties/text",
                    "type": "string",
                    "pattern": "^(.*)$"
                },
                "font": {
                    "$id": "#/properties/font",
                    "type": "string",
                    "pattern": "^(.*)$"
                },
                "size": {
                    "$id": "#/properties/size",
                    "type": "integer"
                },
                "clickable": {
                    "$id": "#/properties/clickable",
                    "type": "boolean"
                },
                "draggable": {
                    "$id": "#/properties/draggable",
                    "type": "boolean"
                }
            }
        }
    },
    "$schema": "http://json-schema.org/draft-07/schema#",
    "$id": "http://example.com/root.json",
    "type": "object",
    "additionalProperties": false,
    "required": [
        "status",
        "response"
    ],
    "properties": {
        "status": {
            "$id": "#/properties/status",
            "type": "string",
            "pattern": "^(.*)$"
        },
        "response": {
            "$id": "#/properties/response",
            "type": "object",
            "additionalProperties": false,
            "required": [
                "game"
            ],
            "properties": {
                "game": {
                    "$id": "#/properties/response/properties/game",
                    "type": "object",
                    "additionalProperties": false,
                    "required": [
                        "name",
                        "author",
                        "gameId",
                        "status",
                        "display"
                    ],
                    "properties": {
                        "name": {
                            "$id": "#/properties/response/properties/game/properties/name",
                            "type": "string",
                            "pattern": "^(.*)$"
                        },
                        "author": {
                            "$id": "#/properties/response/properties/game/properties/author",
                            "type": "string",
                            "pattern": "^(.*)$"
                        },
                        "gameId": {
                            "$id": "#/properties/response/properties/game/properties/gameId",
                            "type": "string",
                            "pattern": "^(.*)$"
                        },
                        "status": {
                            "$id": "#/properties/response/properties/game/properties/status",
                            "type": "string",
                            "pattern": "^(.*)$"
                        },
                        "display": {
                            "$id": "#/properties/response/properties/game/properties/display",
                            "type": "object",
                            "additionalProperties": false,
                            "required": [
                                "canvas",
                                "alert_box",
                                "text_input"
                            ],
                            "properties": {
                                "canvas": {
                                    "$id": "#/properties/response/properties/game/properties/display/properties/canvas",
                                    "type": "object",
                                    "additionalProperties": false,
                                    "required": [
                                        "w",
                                        "h",
                                        "background_image",
                                        "contents"
                                    ],
                                    "properties": {
                                        "w": {
                                            "$id": "#/properties/response/properties/game/properties/display/properties/canvas/properties/w",
                                            "type": "integer"
                                        },
                                        "h": {
                                            "$id": "#/properties/response/properties/game/properties/display/properties/canvas/properties/h",
                                            "type": "integer"
                                        },
                                        "background_image": {
                                            "$id": "#/properties/response/properties/game/properties/display/properties/canvas/properties/background_image",
                                            "type": "object",
                                            "additionalProperties": false,
                                            "required": [
                                                "image"
                                            ],
                                            "properties": {
                                                "image": {
                                                    "$id": "#/properties/response/properties/game/properties/display/properties/canvas/properties/background_image/properties/image",
                                                    "type": "string",
                                                    "pattern": "^(.*)$"
                                                }
                                            }
                                        },
                                        "contents": {
                                            "$id": "#/properties/response/properties/game/properties/display/properties/canvas/properties/contents",
                                            "type": "array",
                                            "items": {
                                                "anyOf": [
                                                    {
                                                        "$ref": "#/definitions/image"
                                                    },
                                                    {
                                                        "$ref": "#/definitions/text"
                                                    }
                                                ]
                                            }
                                        }
                                    }
                                },
                                "alert_box": {
                                    "$id": "#/properties/response/properties/game/properties/display/properties/alert_box",
                                    "type": "object",
                                    "additionalProperties": false,
                                    "required": [
                                        "text"
                                    ],
                                    "properties": {
                                        "text": {
                                            "$id": "#/properties/response/properties/game/properties/display/properties/alert_box/properties/text",
                                            "type": "string",
                                            "pattern": "^(.*)$"
                                        }
                                    }
                                },
                                "text_input": {
                                    "$id": "#/properties/response/properties/game/properties/display/properties/text_input",
                                    "type": "object",
                                    "additionalProperties": false,
                                    "required": [
                                        "message_to_player"
                                    ],
                                    "properties": {
                                        "message_to_player": {
                                            "$id": "#/properties/response/properties/game/properties/display/properties/text_input/properties/message_to_player",
                                            "type": "string",
                                            "pattern": "^(.*)$"
                                        }
                                    }
                                }
                            }
                        }
                    }
                }
            }
        }
    }
}